chaogates/__init__.py
chaogates/chaos_uitls1.py
chaogates/chaos_utils.py
chaogates/chaotic_systems.py
chaogates/circuit_builder.py
chaogates/logic_gates1.py
chaogates/utils2.py
chaogates/visualize.py
chaogates-0.1.0.dist-info/licenses/LICENSE
chaogates-0.1.0.dist-info/METADATA
chaogates-0.1.0.dist-info/WHEEL
chaogates-0.1.0.dist-info/top_level.txt
chaogates-0.1.0.dist-info/RECORD
