Metadata-Version: 2.4
Name: chaogates
Version: 0.1.0
Summary: Chaotic logic gate & circuit simulation toolkit
Author-email: Abhinav Basu <your_email@example.com>
License: MIT
Requires-Python: >=3.9
License-File: LICENSE
Requires-Dist: pandas
Requires-Dist: matplotlib
Requires-Dist: numpy
Requires-Dist: scipy
Provides-Extra: dev
Requires-Dist: pytest; extra == "dev"
Requires-Dist: build; extra == "dev"
Requires-Dist: twine; extra == "dev"
Dynamic: license-file
